availabl.py
availabl_cli-0.0.5.dist-info/METADATA
availabl_cli-0.0.5.dist-info/WHEEL
availabl_cli-0.0.5.dist-info/entry_points.txt
availabl_cli-0.0.5.dist-info/top_level.txt
availabl_cli-0.0.5.dist-info/RECORD
