Metadata-Version: 2.1
Name: availabl-cli
Version: 0.0.5
Summary: availabl cli tool
Author: Arran McCabe
Author-email: arran@availabl.ai
Classifier: Programming Language :: Python :: 3.8
Classifier: Operating System :: OS Independent
Requires-Python: >=3.7
Requires-Dist: boto3 (>=1.26.95)
Requires-Dist: requests (>=2.28.2)
Requires-Dist: click (>=8.1.3)
